LICENSE
README.md
changelog.md
configula/__init__.py
configula/configula.py
configula-0.5.4.dist-info/LICENSE
configula-0.5.4.dist-info/METADATA
configula-0.5.4.dist-info/WHEEL
configula-0.5.4.dist-info/RECORD
