Metadata-Version: 2.1
Name: configula
Version: 0.5.4
Summary: Merges configuration from toml file and environment variables
Home-page: https://github.com/papermerge/configula
License: Apache-2.0
Keywords: configurations,config,environment variables,toml
Author: Eugen Ciur
Author-email: eugen@papermerge.com
Maintainer: Eugen Ciur
Maintainer-email: eugen@papermerge.com
Requires-Python: >=3.8,<4.0
Classifier: License :: OSI Approved :: Apache Software License
Classifier: Operating System :: OS Independent
Classifier: Programming Language :: Python
Classifier: Programming Language :: Python :: 3
Classifier: Programming Language :: Python :: 3.8
Classifier: Programming Language :: Python :: 3.9
Classifier: Programming Language :: Python :: 3.10
Classifier: Programming Language :: Python :: 3.11
Classifier: Programming Language :: Python :: 3 :: Only
Classifier: Programming Language :: Python :: 3.7
Requires-Dist: tomlkit (>=0.7.2,<0.8.0)
Project-URL: Repository, https://github.com/papermerge/configula
